mrsdk/__init__.py
mrsdk/cli.py
mrsdk/client.py
mrsdk/exceptions.py
tests/__init__.py
tests/test_client.py
mrsdk-0.3.1.dist-info/LICENSE
mrsdk-0.3.1.dist-info/METADATA
mrsdk-0.3.1.dist-info/WHEEL
mrsdk-0.3.1.dist-info/entry_points.txt
mrsdk-0.3.1.dist-info/top_level.txt
mrsdk-0.3.1.dist-info/RECORD
