Metadata-Version: 2.2
Name: mrsdk
Version: 0.3.1
Summary: Python SDK for the MindRoot API
Home-page: https://github.com/mindroot/mindroot-python-sdk
Author: MindRoot Team
Author-email: MindRoot Team <info@mindroot.ai>
License: MIT
Project-URL: Homepage, https://github.com/mindroot/mindroot-python-sdk
Project-URL: Bug Tracker, https://github.com/mindroot/mindroot-python-sdk/issues
Classifier: Programming Language :: Python :: 3
Classifier: Programming Language :: Python :: 3.7
Classifier: Programming Language :: Python :: 3.8
Classifier: Programming Language :: Python :: 3.9
Classifier: Programming Language :: Python :: 3.10
Classifier: License :: OSI Approved :: MIT License
Classifier: Operating System :: OS Independent
Classifier: Development Status :: 3 - Alpha
Classifier: Intended Audience :: Developers
Classifier: Topic :: Scientific/Engineering :: Artificial Intelligence
Requires-Python: >=3.7
License-File: LICENSE
Requires-Dist: requests>=2.25.0
Dynamic: author
Dynamic: home-page
Dynamic: requires-python
